fastapi_lifespan_dependencies/__init__.py
fastapi_lifespan_dependencies/exceptions.py
fastapi_lifespan_dependencies/lifespan.py
fastapi_lifespan_dependencies/py.typed
fastapi_lifespan_dependencies-0.1.0.dist-info/LICENSE
fastapi_lifespan_dependencies-0.1.0.dist-info/METADATA
fastapi_lifespan_dependencies-0.1.0.dist-info/WHEEL
fastapi_lifespan_dependencies-0.1.0.dist-info/RECORD
