Metadata-Version: 2.1
Name: fastapi-lifespan-dependencies
Version: 0.1.0
Summary: Allows for the creation of lifespan dependencies - FastAPI dependencies that are only run once per app.
Home-page: https://github.com/Chicken-3001/fastapi-lifespan-dependencies
License: MIT
Author: Ruvi Kaplan
Author-email: thepokoranan@gmail.com
Requires-Python: >=3.12,<4.0
Classifier: License :: OSI Approved :: MIT License
Classifier: Programming Language :: Python :: 3
Classifier: Programming Language :: Python :: 3.12
Requires-Dist: fastapi (>=0.111.0,<0.112.0)
Project-URL: Repository, https://github.com/Chicken-3001/fastapi-lifespan-dependencies
